plutotest/__init__.py
plutotest/pluto.py
plutotest/test.py
plutotest-0.1.1.dist-info/LICENSE.md
plutotest-0.1.1.dist-info/METADATA
plutotest-0.1.1.dist-info/WHEEL
plutotest-0.1.1.dist-info/top_level.txt
plutotest-0.1.1.dist-info/RECORD
